setup.py
src/django_basic_tumblelog.egg-info/PKG-INFO
src/django_basic_tumblelog.egg-info/SOURCES.txt
src/django_basic_tumblelog.egg-info/dependency_links.txt
src/django_basic_tumblelog.egg-info/requires.txt
src/django_basic_tumblelog.egg-info/top_level.txt
src/tumblelog/__init__.py
src/tumblelog/admin.py
src/tumblelog/feeds.py
src/tumblelog/managers.py
src/tumblelog/models.py
src/tumblelog/signals.py
src/tumblelog/sitemap.py
src/tumblelog/tests.py
src/tumblelog/testsettings.py
src/tumblelog/urls.py
src/tumblelog/views.py
src/tumblelog/templatetags/__init__.py
src/tumblelog/templatetags/tumblelog_tags.py