Metadata-Version: 1.0
Name: django-basic-tumblelog
Version: 0.6
Summary: A basic tumblelog application you can add to your Django website.
Home-page: http://myles.github.com/django-basic-tumblelog/
Author: Myles Braithwaite
Author-email: me@mylesbraithwaite.com
License: Apache 2.0
Platform: UNKNOWN
Classifier: Development Status :: 4 - Beta
Classifier: Framework :: Django
Classifier: Intended Audience :: Developers
Classifier: License :: OSI Approved :: Apache Software License
Classifier: Operating System :: OS Independent
Classifier: Programming Language :: Python
Classifier: Topic :: Internet :: WWW/HTTP
